{"kind":"symbol","sections":[],"schemaVersion":{"minor":3,"major":0,"patch":0},"abstract":[{"text":"A secure cryptography library for iOS and macOS that provides cryptographically secure random number generation and encryption capabilities.","type":"text"}],"primaryContentSections":[{"kind":"content","content":[{"type":"heading","text":"Table of Contents","level":2,"anchor":"Table-of-Contents"},{"type":"unorderedList","items":[{"content":[{"inlineContent":[{"identifier":"#features","isActive":true,"type":"reference"}],"type":"paragraph"}]},{"content":[{"type":"paragraph","inlineContent":[{"identifier":"#Requirements","isActive":true,"type":"reference"}]}]},{"content":[{"inlineContent":[{"type":"reference","identifier":"#types-and-algorithms","isActive":true}],"type":"paragraph"}]},{"content":[{"inlineContent":[{"identifier":"doc:\/\/MbSecureCrypto\/documentation\/MbSecureCrypto\/CipherFormat","isActive":true,"type":"reference"}],"type":"paragraph"}]},{"content":[{"type":"paragraph","inlineContent":[{"identifier":"#error-handling","isActive":true,"type":"reference"}]}]},{"content":[{"type":"paragraph","inlineContent":[{"identifier":"#usage-notes","isActive":true,"type":"reference"}]}]},{"content":[{"type":"paragraph","inlineContent":[{"type":"reference","identifier":"#best-practices","isActive":true}]}]},{"content":[{"type":"paragraph","inlineContent":[{"type":"reference","isActive":true,"identifier":"doc:\/\/MbSecureCrypto\/documentation\/MbSecureCrypto\/AESGCM"}]}]},{"content":[{"type":"paragraph","inlineContent":[{"type":"reference","isActive":true,"identifier":"doc:\/\/MbSecureCrypto\/documentation\/MbSecureCrypto\/VersionHistory"}]}]}]},{"type":"heading","level":2,"text":"Features","anchor":"Features"},{"items":[{"content":[{"inlineContent":[{"type":"text","text":"🔒 Cryptographically secure random number generation using Apple’s Security framework"}],"type":"paragraph"}]},{"content":[{"inlineContent":[{"text":"🔐 AES-GCM encryption for strings, data, and files","type":"text"}],"type":"paragraph"}]},{"content":[{"inlineContent":[{"text":"📦 Multiple output formats: raw bytes, hexadecimal, and base64","type":"text"}],"type":"paragraph"}]},{"content":[{"inlineContent":[{"type":"text","text":"⚡️ High-performance implementation using Apple’s CryptoKit"}],"type":"paragraph"}]},{"content":[{"type":"paragraph","inlineContent":[{"text":"🛡️ Side-channel attack protection","type":"text"}]}]},{"content":[{"type":"paragraph","inlineContent":[{"type":"text","text":"✅ Extensive test coverage"}]}]},{"content":[{"type":"paragraph","inlineContent":[{"type":"text","text":"📱 iOS and macOS support"}]}]}],"type":"unorderedList"},{"text":"Requirements","type":"heading","level":2,"anchor":"Requirements"},{"type":"unorderedList","items":[{"content":[{"type":"paragraph","inlineContent":[{"type":"text","text":"iOS 15.6+ \/ macOS 12.4+"}]}]},{"content":[{"type":"paragraph","inlineContent":[{"text":"Xcode 13+","type":"text"}]}]},{"content":[{"inlineContent":[{"text":"Objective-C or Swift projects","type":"text"}],"type":"paragraph"}]}]},{"type":"heading","level":2,"anchor":"Types-and-Algorithms","text":"Types and Algorithms"},{"text":"MBSCipherAlgorithm","type":"heading","anchor":"MBSCipherAlgorithm","level":3},{"code":["typedef NS_ENUM(NSInteger, MBSCipherAlgorithm) {","    MBSCipherAlgorithmAESGCM = 0","} API_AVAILABLE(macos(12.4), ios(15.6));"],"type":"codeListing","syntax":"objectivec"},{"level":3,"anchor":"MBSCipherFormat","text":"MBSCipherFormat","type":"heading"},{"code":["typedef NS_ENUM(uint8_t, MBSCipherFormat) {","    \/\/\/ Format V0: [12B nonce][ciphertext][16B tag]","    MBSCipherFormatV0 = 0","    \/\/\/ Format V1: Universal Secure Block Format","    \/\/\/ Structure: [MAGIC(4)][VER(1)][ALG(1)][PARAMS_LEN(2)][PARAMS(var)][DATA][TAG]","    MBSCipherFormatV1 = 1","} API_AVAILABLE(macos(12.4), ios(15.6));"],"syntax":"objectivec","type":"codeListing"},{"anchor":"Error-Handling","level":2,"type":"heading","text":"Error Handling"},{"type":"heading","anchor":"Random-Operation-Errors-MBSRandomError","text":"Random Operation Errors (MBSRandomError)","level":3},{"syntax":"objectivec","type":"codeListing","code":["typedef NS_ERROR_ENUM(MBSErrorDomain, MBSRandomError) {","    MBSRandomErrorInvalidByteCount = 100,","    MBSRandomErrorGenerationFailed = 101,","    MBSRandomErrorBufferAllocation = 102","};"]},{"text":"Cipher Operation Errors","type":"heading","level":3,"anchor":"Cipher-Operation-Errors"},{"type":"codeListing","syntax":"objectivec","code":["typedef NS_ERROR_ENUM(MBSErrorDomain, MBSCipherError) {","    \/\/ Input validation errors","    MBSCipherErrorInvalidKey = 200,           \/\/ Key size doesn't match algorithm requirements","    MBSCipherErrorInvalidIV = 201,            \/\/ IV\/nonce is invalid or wrong size","    MBSCipherErrorInvalidInput = 202,         \/\/ Input data is invalid or corrupted","    MBSCipherErrorUnsupportedAlgorithm = 203, \/\/ Requested algorithm is not supported","    MBSCipherErrorUnsupportedFormat = 204,    \/\/ Unknown or unsupported format version","    MBSCipherErrorFormatDetectionFailed = 205, \/\/ Failed to detect format version","    MBSCipherErrorFormatMismatch = 206,       \/\/ Format version mismatch during decryption","    ","    \/\/ Operation errors","    MBSCipherErrorEncryptionFailed = 210,     \/\/ Encryption operation failed","    MBSCipherErrorDecryptionFailed = 211,     \/\/ Decryption operation failed","    MBSCipherErrorAuthenticationFailed = 212,  \/\/ Authentication tag verification failed","    ","    \/\/ File operation errors","    MBSCipherErrorIOFailure = 220,            \/\/ File read\/write operation failed","    MBSCipherErrorFileTooLarge = 221,         \/\/ File exceeds size limit","    MBSCipherErrorFilePermission = 222        \/\/ Insufficient permission to access file","};"]},{"anchor":"Usage-Notes","level":2,"text":"Usage Notes","type":"heading"},{"type":"orderedList","items":[{"content":[{"inlineContent":[{"type":"text","text":"Format parameter is optional, defaults to V0"}],"type":"paragraph"}]},{"content":[{"inlineContent":[{"text":"When decrypting, format detection is automatic if not specified","type":"text"}],"type":"paragraph"}]},{"content":[{"type":"paragraph","inlineContent":[{"type":"text","text":"Encrypted output includes format version, nonce, and authentication tag"}]}]},{"content":[{"type":"paragraph","inlineContent":[{"text":"All operations maintain backward compatibility","type":"text"}]}]},{"content":[{"inlineContent":[{"type":"text","text":"Maximum file size limit: 10MB"}],"type":"paragraph"}]}]},{"type":"heading","level":2,"anchor":"Best-Practices","text":"Best Practices"},{"type":"orderedList","items":[{"content":[{"inlineContent":[{"inlineContent":[{"type":"text","text":"Key Management"}],"type":"strong"}],"type":"paragraph"},{"items":[{"content":[{"type":"paragraph","inlineContent":[{"text":"Generate keys using ","type":"text"},{"type":"codeVoice","code":"MBSRandom generateBytes:error:"}]}]},{"content":[{"type":"paragraph","inlineContent":[{"type":"text","text":"Store keys securely in Keychain"}]}]},{"content":[{"inlineContent":[{"type":"text","text":"Use unique keys for each encryption operation"}],"type":"paragraph"}]},{"content":[{"inlineContent":[{"type":"text","text":"Implement proper key rotation"}],"type":"paragraph"}]}],"type":"unorderedList"}]},{"content":[{"type":"paragraph","inlineContent":[{"inlineContent":[{"type":"text","text":"Memory Security"}],"type":"strong"}]},{"items":[{"content":[{"type":"paragraph","inlineContent":[{"text":"Zero sensitive data after use","type":"text"}]}]},{"content":[{"inlineContent":[{"type":"text","text":"Use autoreleasepool for deterministic cleanup"}],"type":"paragraph"}]},{"content":[{"inlineContent":[{"type":"text","text":"Avoid logging sensitive information"}],"type":"paragraph"}]}],"type":"unorderedList"}]},{"content":[{"type":"paragraph","inlineContent":[{"inlineContent":[{"type":"text","text":"Error Handling"}],"type":"strong"}]},{"type":"unorderedList","items":[{"content":[{"inlineContent":[{"text":"Always check error return values","type":"text"}],"type":"paragraph"}]},{"content":[{"inlineContent":[{"text":"Handle all error cases appropriately","type":"text"}],"type":"paragraph"}]},{"content":[{"type":"paragraph","inlineContent":[{"text":"Avoid exposing sensitive information in errors","type":"text"}]}]}]}]},{"content":[{"type":"paragraph","inlineContent":[{"type":"strong","inlineContent":[{"text":"File Operations","type":"text"}]}]},{"items":[{"content":[{"type":"paragraph","inlineContent":[{"text":"Respect the 10MB file size limit","type":"text"}]}]},{"content":[{"inlineContent":[{"type":"text","text":"Use atomic file operations"}],"type":"paragraph"}]},{"content":[{"type":"paragraph","inlineContent":[{"text":"Clean up temporary files","type":"text"}]}]}],"type":"unorderedList"}]}]}]}],"hierarchy":{"paths":[[]]},"topicSections":[{"anchor":"Error-Handling","title":"Error Handling","identifiers":["doc:\/\/MbSecureCrypto\/documentation\/MbSecureCrypto\/MBSRandomError-swift.struct\/Code","doc:\/\/MbSecureCrypto\/documentation\/MbSecureCrypto\/MBSCipherError-swift.struct\/Code"]},{"anchor":"Articles","generated":true,"identifiers":["doc:\/\/MbSecureCrypto\/documentation\/MbSecureCrypto\/AESGCM","doc:\/\/MbSecureCrypto\/documentation\/MbSecureCrypto\/CipherFormat","doc:\/\/MbSecureCrypto\/documentation\/MbSecureCrypto\/VersionHistory"],"title":"Articles"},{"identifiers":["doc:\/\/MbSecureCrypto\/documentation\/MbSecureCrypto\/MBSCipherBridge"],"title":"Classes","generated":true,"anchor":"Classes"},{"identifiers":["doc:\/\/MbSecureCrypto\/documentation\/MbSecureCrypto\/MBSCipherError-swift.struct","doc:\/\/MbSecureCrypto\/documentation\/MbSecureCrypto\/MBSRandomError-swift.struct"],"title":"Structures","generated":true,"anchor":"Structures"},{"anchor":"Variables","generated":true,"identifiers":["doc:\/\/MbSecureCrypto\/documentation\/MbSecureCrypto\/MBSErrorDomain","doc:\/\/MbSecureCrypto\/documentation\/MbSecureCrypto\/kMBSCipherMaxFileSize"],"title":"Variables"},{"identifiers":["doc:\/\/MbSecureCrypto\/documentation\/MbSecureCrypto\/MBSCipherAlgorithm","doc:\/\/MbSecureCrypto\/documentation\/MbSecureCrypto\/MBSCipherFormat"],"anchor":"Enumerations","title":"Enumerations","generated":true}],"variants":[{"traits":[{"interfaceLanguage":"swift"}],"paths":["\/documentation\/mbsecurecrypto"]},{"paths":["\/documentation\/mbsecurecrypto"],"traits":[{"interfaceLanguage":"occ"}]}],"metadata":{"role":"collection","modules":[{"name":"MbSecureCrypto"}],"title":"MbSecureCrypto","externalID":"MbSecureCrypto","symbolKind":"module","roleHeading":"Framework"},"identifier":{"url":"doc:\/\/MbSecureCrypto\/documentation\/MbSecureCrypto","interfaceLanguage":"swift"},"references":{"doc://MbSecureCrypto/documentation/MbSecureCrypto/MBSRandomError-swift.struct/Code":{"role":"symbol","type":"topic","url":"\/documentation\/mbsecurecrypto\/mbsrandomerror-swift.struct\/code","kind":"symbol","navigatorTitle":[{"kind":"identifier","text":"Code"}],"identifier":"doc:\/\/MbSecureCrypto\/documentation\/MbSecureCrypto\/MBSRandomError-swift.struct\/Code","abstract":[{"type":"text","text":"Error codes for Random operations."}],"title":"MBSRandomError.Code","fragments":[{"kind":"keyword","text":"enum"},{"text":" ","kind":"text"},{"text":"Code","kind":"identifier"}]},"doc://MbSecureCrypto/documentation/MbSecureCrypto/MBSCipher":{"fragments":[{"kind":"identifier","text":"MBSCipher"}],"title":"MBSCipher","kind":"symbol","type":"topic","identifier":"doc:\/\/MbSecureCrypto\/documentation\/MbSecureCrypto\/MBSCipher","url":"\/documentation\/mbsecurecrypto\/mbscipher","abstract":[{"type":"text","text":"A secure encryption and decryption utility that implements authenticated encryption."}],"role":"symbol"},"doc://MbSecureCrypto/documentation/MbSecureCrypto/VersionHistory":{"url":"\/documentation\/mbsecurecrypto\/versionhistory","type":"topic","kind":"article","title":"Version History","abstract":[],"role":"article","identifier":"doc:\/\/MbSecureCrypto\/documentation\/MbSecureCrypto\/VersionHistory"},"doc://MbSecureCrypto/documentation/MbSecureCrypto/MBSCipherFormat":{"type":"topic","navigatorTitle":[{"text":"MBSCipherFormat","kind":"identifier"}],"kind":"symbol","title":"MBSCipherFormat","fragments":[{"kind":"keyword","text":"enum"},{"kind":"text","text":" "},{"text":"MBSCipherFormat","kind":"identifier"}],"url":"\/documentation\/mbsecurecrypto\/mbscipherformat","identifier":"doc:\/\/MbSecureCrypto\/documentation\/MbSecureCrypto\/MBSCipherFormat","abstract":[{"text":"Supported ciphertext format versions","type":"text"}],"role":"symbol"},"doc://MbSecureCrypto/documentation/MbSecureCrypto/MBSCipherError-swift.struct/Code":{"title":"MBSCipherError.Code","fragments":[{"kind":"keyword","text":"enum"},{"text":" ","kind":"text"},{"text":"Code","kind":"identifier"}],"role":"symbol","type":"topic","identifier":"doc:\/\/MbSecureCrypto\/documentation\/MbSecureCrypto\/MBSCipherError-swift.struct\/Code","kind":"symbol","url":"\/documentation\/mbsecurecrypto\/mbsciphererror-swift.struct\/code","abstract":[{"type":"text","text":"Error codes for cipher operations"}],"navigatorTitle":[{"text":"Code","kind":"identifier"}]},"#Requirements":{"url":"#Requirements","type":"link","identifier":"#Requirements","titleInlineContent":[{"text":"Requirements","type":"text"}],"title":"Requirements"},"doc://MbSecureCrypto/documentation/MbSecureCrypto/kMBSCipherMaxFileSize":{"kind":"symbol","role":"symbol","fragments":[{"text":"let","kind":"keyword"},{"text":" ","kind":"text"},{"text":"kMBSCipherMaxFileSize","kind":"identifier"},{"text":": ","kind":"text"},{"text":"UInt","kind":"typeIdentifier","preciseIdentifier":"s:Su"}],"title":"kMBSCipherMaxFileSize","url":"\/documentation\/mbsecurecrypto\/kmbsciphermaxfilesize","navigatorTitle":[{"kind":"identifier","text":"kMBSCipherMaxFileSize"}],"abstract":[],"identifier":"doc:\/\/MbSecureCrypto\/documentation\/MbSecureCrypto\/kMBSCipherMaxFileSize","type":"topic"},"doc://MbSecureCrypto/documentation/MbSecureCrypto/MBSHkdfAlgorithm":{"title":"MBSHkdfAlgorithm","identifier":"doc:\/\/MbSecureCrypto\/documentation\/MbSecureCrypto\/MBSHkdfAlgorithm","role":"symbol","url":"\/documentation\/mbsecurecrypto\/mbshkdfalgorithm","type":"topic","abstract":[{"text":"Supported HKDF algorithms with their corresponding HMAC functions.","type":"text"}],"kind":"symbol","fragments":[{"text":"MBSHkdfAlgorithm","kind":"identifier"}]},"#types-and-algorithms":{"url":"#types-and-algorithms","type":"link","identifier":"#types-and-algorithms","titleInlineContent":[{"text":"Types & Algorithms","type":"text"}],"title":"Types & Algorithms"},"doc://MbSecureCrypto/documentation/MbSecureCrypto/MBSCipherAlgorithm":{"type":"topic","navigatorTitle":[{"text":"MBSCipherAlgorithm","kind":"identifier"}],"kind":"symbol","title":"MBSCipherAlgorithm","fragments":[{"text":"enum","kind":"keyword"},{"kind":"text","text":" "},{"kind":"identifier","text":"MBSCipherAlgorithm"}],"url":"\/documentation\/mbsecurecrypto\/mbscipheralgorithm","identifier":"doc:\/\/MbSecureCrypto\/documentation\/MbSecureCrypto\/MBSCipherAlgorithm","abstract":[{"text":"Supported Cipher Algorithms","type":"text"}],"role":"symbol"},"#error-handling":{"type":"link","title":"Error Handling","titleInlineContent":[{"type":"text","text":"Error Handling"}],"identifier":"#error-handling","url":"#error-handling"},"doc://MbSecureCrypto/documentation/MbSecureCrypto/MBSKeyDerivation":{"type":"topic","kind":"symbol","title":"MBSKeyDerivation","fragments":[{"text":"MBSKeyDerivation","kind":"identifier"}],"url":"\/documentation\/mbsecurecrypto\/mbskeyderivation","identifier":"doc:\/\/MbSecureCrypto\/documentation\/MbSecureCrypto\/MBSKeyDerivation","abstract":[{"text":"A secure key derivation utility that implements HKDF (RFC 5869).","type":"text"}],"role":"symbol"},"doc://MbSecureCrypto/documentation/MbSecureCrypto/MBSCipherError-swift.struct":{"kind":"symbol","title":"MBSCipherError","url":"\/documentation\/mbsecurecrypto\/mbsciphererror-swift.struct","role":"symbol","navigatorTitle":[{"text":"MBSCipherError","kind":"identifier"}],"type":"topic","identifier":"doc:\/\/MbSecureCrypto\/documentation\/MbSecureCrypto\/MBSCipherError-swift.struct","abstract":[],"fragments":[{"text":"struct","kind":"keyword"},{"kind":"text","text":" "},{"kind":"identifier","text":"MBSCipherError"}]},"doc://MbSecureCrypto/documentation/MbSecureCrypto":{"kind":"symbol","title":"MbSecureCrypto","url":"\/documentation\/mbsecurecrypto","role":"collection","type":"topic","identifier":"doc:\/\/MbSecureCrypto\/documentation\/MbSecureCrypto","abstract":[{"text":"A secure cryptography library for iOS and macOS that provides cryptographically secure random number generation and encryption capabilities.","type":"text"}]},"#usage-notes":{"type":"link","title":"Usage Notes","titleInlineContent":[{"type":"text","text":"Usage Notes"}],"identifier":"#usage-notes","url":"#usage-notes"},"#features":{"type":"link","title":"Features","titleInlineContent":[{"text":"Features","type":"text"}],"identifier":"#features","url":"#features"},"doc://MbSecureCrypto/documentation/MbSecureCrypto/MBSCipherBridge":{"fragments":[{"text":"class","kind":"keyword"},{"kind":"text","text":" "},{"kind":"identifier","text":"MBSCipherBridge"}],"navigatorTitle":[{"text":"MBSCipherBridge","kind":"identifier"}],"kind":"symbol","abstract":[{"text":"Internal use only","type":"text"}],"type":"topic","identifier":"doc:\/\/MbSecureCrypto\/documentation\/MbSecureCrypto\/MBSCipherBridge","role":"symbol","title":"MBSCipherBridge","url":"\/documentation\/mbsecurecrypto\/mbscipherbridge"},"doc://MbSecureCrypto/documentation/MbSecureCrypto/CipherFormat":{"url":"\/documentation\/mbsecurecrypto\/cipherformat","type":"topic","kind":"article","title":"Cipher Format","abstract":[],"role":"article","identifier":"doc:\/\/MbSecureCrypto\/documentation\/MbSecureCrypto\/CipherFormat"},"#best-practices":{"type":"link","title":"Best Practices","titleInlineContent":[{"text":"Best Practices","type":"text"}],"identifier":"#best-practices","url":"#best-practices"},"doc://MbSecureCrypto/documentation/MbSecureCrypto/MbSecureCryptoVersionString":{"fragments":[{"text":"MbSecureCryptoVersionString","kind":"identifier"}],"kind":"symbol","abstract":[{"type":"text","text":"Project version string"}],"type":"topic","identifier":"doc:\/\/MbSecureCrypto\/documentation\/MbSecureCrypto\/MbSecureCryptoVersionString","role":"symbol","title":"MbSecureCryptoVersionString","url":"\/documentation\/mbsecurecrypto\/mbsecurecryptoversionstring"},"doc://MbSecureCrypto/documentation/MbSecureCrypto/MBSErrorDomain":{"navigatorTitle":[{"kind":"identifier","text":"MBSErrorDomain"}],"type":"topic","fragments":[{"text":"let","kind":"keyword"},{"text":" ","kind":"text"},{"kind":"identifier","text":"MBSErrorDomain"},{"text":": ","kind":"text"},{"preciseIdentifier":"s:SS","text":"String","kind":"typeIdentifier"}],"kind":"symbol","abstract":[],"url":"\/documentation\/mbsecurecrypto\/mbserrordomain","role":"symbol","identifier":"doc:\/\/MbSecureCrypto\/documentation\/MbSecureCrypto\/MBSErrorDomain","title":"MBSErrorDomain"},"doc://MbSecureCrypto/documentation/MbSecureCrypto/MBSRandomError-swift.struct":{"fragments":[{"text":"struct","kind":"keyword"},{"kind":"text","text":" "},{"text":"MBSRandomError","kind":"identifier"}],"abstract":[],"type":"topic","url":"\/documentation\/mbsecurecrypto\/mbsrandomerror-swift.struct","identifier":"doc:\/\/MbSecureCrypto\/documentation\/MbSecureCrypto\/MBSRandomError-swift.struct","role":"symbol","kind":"symbol","title":"MBSRandomError","navigatorTitle":[{"text":"MBSRandomError","kind":"identifier"}]},"doc://MbSecureCrypto/documentation/MbSecureCrypto/MbSecureCryptoVersionNumber":{"url":"\/documentation\/mbsecurecrypto\/mbsecurecryptoversionnumber","kind":"symbol","role":"symbol","fragments":[{"text":"MbSecureCryptoVersionNumber","kind":"identifier"}],"title":"MbSecureCryptoVersionNumber","abstract":[{"type":"text","text":"Project version number"}],"identifier":"doc:\/\/MbSecureCrypto\/documentation\/MbSecureCrypto\/MbSecureCryptoVersionNumber","type":"topic"},"doc://MbSecureCrypto/documentation/MbSecureCrypto/AESGCM":{"url":"\/documentation\/mbsecurecrypto\/aesgcm","type":"topic","kind":"article","title":"AES-GCM","abstract":[],"role":"article","identifier":"doc:\/\/MbSecureCrypto\/documentation\/MbSecureCrypto\/AESGCM"},"doc://MbSecureCrypto/documentation/MbSecureCrypto/MBSRandom":{"identifier":"doc:\/\/MbSecureCrypto\/documentation\/MbSecureCrypto\/MBSRandom","abstract":[{"type":"text","text":"A utility class that provides cryptographically secure random number generation."}],"kind":"symbol","title":"MBSRandom","type":"topic","url":"\/documentation\/mbsecurecrypto\/mbsrandom","fragments":[{"kind":"identifier","text":"MBSRandom"}],"role":"symbol"}},"variantOverrides":[{"traits":[{"interfaceLanguage":"occ"}],"patch":[{"path":"\/identifier\/interfaceLanguage","value":"occ","op":"replace"},{"op":"replace","path":"\/topicSections","value":[{"anchor":"Essentials","title":"Essentials","identifiers":["doc:\/\/MbSecureCrypto\/documentation\/MbSecureCrypto\/MBSRandom","doc:\/\/MbSecureCrypto\/documentation\/MbSecureCrypto\/MBSCipher","doc:\/\/MbSecureCrypto\/documentation\/MbSecureCrypto\/MBSKeyDerivation"]},{"identifiers":["doc:\/\/MbSecureCrypto\/documentation\/MbSecureCrypto\/MBSRandomError-swift.struct\/Code","doc:\/\/MbSecureCrypto\/documentation\/MbSecureCrypto\/MBSCipherError-swift.struct\/Code"],"anchor":"Error-Handling","title":"Error Handling"},{"anchor":"Articles","title":"Articles","generated":true,"identifiers":["doc:\/\/MbSecureCrypto\/documentation\/MbSecureCrypto\/AESGCM","doc:\/\/MbSecureCrypto\/documentation\/MbSecureCrypto\/CipherFormat","doc:\/\/MbSecureCrypto\/documentation\/MbSecureCrypto\/VersionHistory"]},{"generated":true,"identifiers":["doc:\/\/MbSecureCrypto\/documentation\/MbSecureCrypto\/MBSCipherBridge"],"anchor":"Classes","title":"Classes"},{"anchor":"Variables","title":"Variables","identifiers":["doc:\/\/MbSecureCrypto\/documentation\/MbSecureCrypto\/MBSErrorDomain","doc:\/\/MbSecureCrypto\/documentation\/MbSecureCrypto\/MbSecureCryptoVersionNumber","doc:\/\/MbSecureCrypto\/documentation\/MbSecureCrypto\/MbSecureCryptoVersionString","doc:\/\/MbSecureCrypto\/documentation\/MbSecureCrypto\/kMBSCipherMaxFileSize"],"generated":true},{"anchor":"Enumerations","title":"Enumerations","generated":true,"identifiers":["doc:\/\/MbSecureCrypto\/documentation\/MbSecureCrypto\/MBSCipherAlgorithm","doc:\/\/MbSecureCrypto\/documentation\/MbSecureCrypto\/MBSCipherFormat","doc:\/\/MbSecureCrypto\/documentation\/MbSecureCrypto\/MBSHkdfAlgorithm"]}]},{"path":"\/relationshipsSections","value":null,"op":"add"},{"op":"add","path":"\/seeAlsoSections","value":null},{"op":"replace","path":"\/references\/doc:~1~1MbSecureCrypto~1documentation~1MbSecureCrypto~1MBSRandomError-swift.struct~1Code\/title","value":"MBSRandomError"},{"op":"replace","value":[{"text":"MBSRandomError","kind":"identifier"}],"path":"\/references\/doc:~1~1MbSecureCrypto~1documentation~1MbSecureCrypto~1MBSRandomError-swift.struct~1Code\/fragments"},{"value":[{"text":"MBSRandomError","kind":"identifier"}],"op":"replace","path":"\/references\/doc:~1~1MbSecureCrypto~1documentation~1MbSecureCrypto~1MBSRandomError-swift.struct~1Code\/navigatorTitle"},{"path":"\/references\/doc:~1~1MbSecureCrypto~1documentation~1MbSecureCrypto~1MBSCipherFormat\/title","value":"MBSCipherFormat","op":"replace"},{"value":[{"kind":"identifier","text":"MBSCipherFormat"}],"path":"\/references\/doc:~1~1MbSecureCrypto~1documentation~1MbSecureCrypto~1MBSCipherFormat\/fragments","op":"replace"},{"op":"replace","path":"\/references\/doc:~1~1MbSecureCrypto~1documentation~1MbSecureCrypto~1MBSCipherFormat\/navigatorTitle","value":[{"kind":"identifier","text":"MBSCipherFormat"}]},{"op":"replace","path":"\/references\/doc:~1~1MbSecureCrypto~1documentation~1MbSecureCrypto~1MBSCipherError-swift.struct~1Code\/title","value":"MBSCipherError"},{"path":"\/references\/doc:~1~1MbSecureCrypto~1documentation~1MbSecureCrypto~1MBSCipherError-swift.struct~1Code\/fragments","value":[{"text":"MBSCipherError","kind":"identifier"}],"op":"replace"},{"op":"replace","path":"\/references\/doc:~1~1MbSecureCrypto~1documentation~1MbSecureCrypto~1MBSCipherError-swift.struct~1Code\/navigatorTitle","value":[{"kind":"identifier","text":"MBSCipherError"}]},{"value":"kMBSCipherMaxFileSize","op":"replace","path":"\/references\/doc:~1~1MbSecureCrypto~1documentation~1MbSecureCrypto~1kMBSCipherMaxFileSize\/title"},{"op":"replace","path":"\/references\/doc:~1~1MbSecureCrypto~1documentation~1MbSecureCrypto~1kMBSCipherMaxFileSize\/fragments","value":[{"text":"kMBSCipherMaxFileSize","kind":"identifier"}]},{"value":"MBSCipherAlgorithm","op":"replace","path":"\/references\/doc:~1~1MbSecureCrypto~1documentation~1MbSecureCrypto~1MBSCipherAlgorithm\/title"},{"path":"\/references\/doc:~1~1MbSecureCrypto~1documentation~1MbSecureCrypto~1MBSCipherAlgorithm\/fragments","op":"replace","value":[{"text":"MBSCipherAlgorithm","kind":"identifier"}]},{"op":"replace","path":"\/references\/doc:~1~1MbSecureCrypto~1documentation~1MbSecureCrypto~1MBSCipherAlgorithm\/navigatorTitle","value":[{"kind":"identifier","text":"MBSCipherAlgorithm"}]},{"op":"replace","path":"\/references\/doc:~1~1MbSecureCrypto~1documentation~1MbSecureCrypto~1MBSCipherBridge\/title","value":"MBSCipherBridge"},{"path":"\/references\/doc:~1~1MbSecureCrypto~1documentation~1MbSecureCrypto~1MBSCipherBridge\/fragments","value":[{"text":"MBSCipherBridge","kind":"identifier"}],"op":"replace"},{"op":"replace","path":"\/references\/doc:~1~1MbSecureCrypto~1documentation~1MbSecureCrypto~1MBSCipherBridge\/navigatorTitle","value":[{"text":"MBSCipherBridge","kind":"identifier"}]},{"path":"\/references\/doc:~1~1MbSecureCrypto~1documentation~1MbSecureCrypto~1MBSErrorDomain\/title","value":"MBSErrorDomain","op":"replace"},{"path":"\/references\/doc:~1~1MbSecureCrypto~1documentation~1MbSecureCrypto~1MBSErrorDomain\/fragments","op":"replace","value":[{"text":"MBSErrorDomain","kind":"identifier"}]}]}]}